emg_fatigue_detection_toolbox-0.1.4.dist-info/licenses/LICENSE
emg_fd/__init__.py
emg_fd/models/fatigue_model_bundle.joblib
emg_fd/src/__init__.py
emg_fd/src/pipeline/__init__.py
emg_fd/src/pipeline/inference.py
emg_fd/src/pipeline/signal_analysis_pipeline.py
emg_fd/src/pipeline/train_model.py
emg_fd/src/utils/__init__.py
emg_fd/src/utils/data_utils.py
emg_fd/src/utils/emg_processing_utils.py
emg_fd/src/utils/eval_utils.py
emg_fd/src/utils/ml_utils.py
emg_fd/src/utils/plot_utils.py
emg_fd/src/utils/print_utils.py
emg_fatigue_detection_toolbox-0.1.4.dist-info/METADATA
emg_fatigue_detection_toolbox-0.1.4.dist-info/WHEEL
emg_fatigue_detection_toolbox-0.1.4.dist-info/top_level.txt
emg_fatigue_detection_toolbox-0.1.4.dist-info/RECORD
