Metadata-Version: 2.4
Name: emg-fatigue-detection-toolbox
Version: 0.1.4
Summary: EMG fatigue detection (training + inference) with a packaged pretrained model.
Author-email: Muhammad Muqsit Islam <islammuqsit7@gmail.com>
License: MIT License
Keywords: EMG,fatigue,biomechanics,machine-learning
Classifier: Programming Language :: Python :: 3
Classifier: Programming Language :: Python :: 3 :: Only
Classifier: License :: OSI Approved :: MIT License
Classifier: Operating System :: OS Independent
Requires-Python: >=3.10
License-File: LICENSE
Requires-Dist: matplotlib~=3.9
Requires-Dist: numpy~=2.2.6
Requires-Dist: pyomeca~=2024.0.2
Requires-Dist: scipy~=1.15.3
Requires-Dist: pandas~=2.3.3
Requires-Dist: seaborn
Requires-Dist: scikit-learn~=1.7.2
Requires-Dist: joblib~=1.5.2
Dynamic: license-file
